slint-1.14.1b1.dist-info/METADATA
slint-1.14.1b1.dist-info/WHEEL
slint/__init__.py
slint/loop.py
slint/models.py
slint/py.typed
slint/slint.pyd
slint/slint.pyi
slint-1.14.1b1.dist-info/RECORD
